taskiq_nats/__init__.py
taskiq_nats/broker.py
taskiq_nats/py.typed
taskiq_nats/result_backend.py
taskiq_nats/schedule_source.py
taskiq_nats-0.5.1.dist-info/METADATA
taskiq_nats-0.5.1.dist-info/WHEEL
taskiq_nats-0.5.1.dist-info/RECORD
