Metadata-Version: 2.1
Name: taskiq-nats
Version: 0.5.1
Summary: NATS integration for taskiq
Home-page: https://github.com/taskiq-python/taskiq-nats
Keywords: taskiq,tasks,distributed,async,nats,result_backend
Author: taskiq-team
Author-email: taskiq@norely.com
Requires-Python: >=3.8.1,<4.0.0
Classifier: Programming Language :: Python
Classifier: Programming Language :: Python :: 3
Classifier: Programming Language :: Python :: 3.9
Classifier: Programming Language :: Python :: 3.10
Classifier: Programming Language :: Python :: 3.11
Classifier: Programming Language :: Python :: 3.12
Classifier: Programming Language :: Python :: 3.13
Classifier: Programming Language :: Python :: 3 :: Only
Classifier: Programming Language :: Python :: 3.8
Requires-Dist: nats-py (>=2.2.0,<3.0.0)
Requires-Dist: taskiq (>=0.8,<1)
Project-URL: Repository, https://github.com/taskiq-python/taskiq-nats
